lythp.py
lythp-0.0.1.dist-info/LICENSE
lythp-0.0.1.dist-info/METADATA
lythp-0.0.1.dist-info/WHEEL
lythp-0.0.1.dist-info/top_level.txt
lythp-0.0.1.dist-info/RECORD
