Metadata-Version: 2.1
Name: lythp
Version: 0.0.1
Summary: Python as a LISP
Author-email: B AG <bayersglassey@gmail.com>
Project-URL: Homepage, https://github.com/bayersglassey/lythp
Classifier: Programming Language :: Python :: 3
Classifier: Operating System :: OS Independent
Requires-Python: >=3.8
License-File: LICENSE
